pyfebio/__init__.py
pyfebio/_types.py
pyfebio/boundary.py
pyfebio/constraints.py
pyfebio/contact.py
pyfebio/control.py
pyfebio/discrete.py
pyfebio/globals.py
pyfebio/include.py
pyfebio/initial.py
pyfebio/loaddata.py
pyfebio/loads.py
pyfebio/material.py
pyfebio/mesh.py
pyfebio/meshadaptor.py
pyfebio/meshdata.py
pyfebio/meshdomains.py
pyfebio/model.py
pyfebio/module.py
pyfebio/output.py
pyfebio/py.typed
pyfebio/rigid.py
pyfebio/step.py
pyfebio/xplt.py
pyfebio-0.1.2.dist-info/WHEEL
pyfebio-0.1.2.dist-info/METADATA
pyfebio-0.1.2.dist-info/RECORD
