Metadata-Version: 2.4
Name: pyfebio
Version: 0.1.2
Summary: A Python API for the FEBio finite element solver.
Author: Scott Sibole
Author-email: Scott Sibole <scott.sibole@gmail.com>
License-Expression: MIT
Requires-Dist: h5py>=3.15.1
Requires-Dist: lxml>=6.0.1
Requires-Dist: meshio[all]>=5.3.5
Requires-Dist: pydantic-xml>=2.17.3
Requires-Python: >=3.11
